<?xml version="1.0" encoding="UTF-8"?>
<Training_Data>
  <Generation>
    <AverageFitness>1.256</AverageFitness>
    <TotalFitness>314.0</TotalFitness>
    <BestFitness>64.0</BestFitness>
  </Generation>
  <Generation>
    <AverageFitness>71.504</AverageFitness>
    <TotalFitness>17876.0</TotalFitness>
    <BestFitness>9261.0</BestFitness>
  </Generation>
  <Generation>
    <AverageFitness>861.5</AverageFitness>
    <TotalFitness>215375.0</TotalFitness>
    <BestFitness>12167.0</BestFitness>
  </Generation>
  <Generation>
    <AverageFitness>1428.66</AverageFitness>
    <TotalFitness>357165.0</TotalFitness>
    <BestFitness>13824.0</BestFitness>
  </Generation>
  <Generation>
    <AverageFitness>1754.936</AverageFitness>
    <TotalFitness>438734.0</TotalFitness>
    <BestFitness>13824.0</BestFitness>
  </Generation>
  <Generation>
    <AverageFitness>2032.816</AverageFitness>
    <TotalFitness>508204.0</TotalFitness>
    <BestFitness>13824.0</BestFitness>
  </Generation>
  <Generation>
    <AverageFitness>2444.96</AverageFitness>
    <TotalFitness>611240.0</TotalFitness>
    <BestFitness>15625.0</BestFitness>
  </Generation>
  <Generation>
    <AverageFitness>2982.104</AverageFitness>
    <TotalFitness>745526.0</TotalFitness>
    <BestFitness>15625.0</BestFitness>
  </Generation>
  <Generation>
    <AverageFitness>3012.152</AverageFitness>
    <TotalFitness>753038.0</TotalFitness>
    <BestFitness>15625.0</BestFitness>
  </Generation>
  <Generation>
    <AverageFitness>3446.088</AverageFitness>
    <TotalFitness>861522.0</TotalFitness>
    <BestFitness>21952.0</BestFitness>
  </Generation>
  <Generation>
    <AverageFitness>3886.6</AverageFitness>
    <TotalFitness>971650.0</TotalFitness>
    <BestFitness>17576.0</BestFitness>
  </Generation>
  <Generation>
    <AverageFitness>5291.58</AverageFitness>
    <TotalFitness>1322895.0</TotalFitness>
    <BestFitness>21952.0</BestFitness>
  </Generation>
  <Generation>
    <AverageFitness>6075.884</AverageFitness>
    <TotalFitness>1518971.0</TotalFitness>
    <BestFitness>21952.0</BestFitness>
  </Generation>
  <Generation>
    <AverageFitness>8677.804</AverageFitness>
    <TotalFitness>2169451.0</TotalFitness>
    <BestFitness>27000.0</BestFitness>
  </Generation>
  <Generation>
    <AverageFitness>10912.7</AverageFitness>
    <TotalFitness>2728175.0</TotalFitness>
    <BestFitness>21952.0</BestFitness>
  </Generation>
  <Generation>
    <AverageFitness>11045.872</AverageFitness>
    <TotalFitness>2761468.0</TotalFitness>
    <BestFitness>35937.0</BestFitness>
  </Generation>
  <Generation>
    <AverageFitness>12113.208</AverageFitness>
    <TotalFitness>3028302.0</TotalFitness>
    <BestFitness>27000.0</BestFitness>
  </Generation>
  <Generation>
    <AverageFitness>13016.1</AverageFitness>
    <TotalFitness>3254025.0</TotalFitness>
    <BestFitness>21952.0</BestFitness>
  </Generation>
  <Generation>
    <AverageFitness>13367.648</AverageFitness>
    <TotalFitness>3341912.0</TotalFitness>
    <BestFitness>24389.0</BestFitness>
  </Generation>
  <Generation>
    <AverageFitness>13355.024</AverageFitness>
    <TotalFitness>3338756.0</TotalFitness>
    <BestFitness>29791.0</BestFitness>
  </Generation>
  <Generation>
    <AverageFitness>13825.612</AverageFitness>
    <TotalFitness>3456403.0</TotalFitness>
    <BestFitness>24389.0</BestFitness>
  </Generation>
  <Generation>
    <AverageFitness>13535.096</AverageFitness>
    <TotalFitness>3383774.0</TotalFitness>
    <BestFitness>24389.0</BestFitness>
  </Generation>
  <Generation>
    <AverageFitness>13806.376</AverageFitness>
    <TotalFitness>3451594.0</TotalFitness>
    <BestFitness>24389.0</BestFitness>
  </Generation>
  <Generation>
    <AverageFitness>13538.904</AverageFitness>
    <TotalFitness>3384726.0</TotalFitness>
    <BestFitness>24389.0</BestFitness>
  </Generation>
  <Generation>
    <AverageFitness>13668.484</AverageFitness>
    <TotalFitness>3417121.0</TotalFitness>
    <BestFitness>24389.0</BestFitness>
  </Generation>
  <Generation>
    <AverageFitness>12633.96</AverageFitness>
    <TotalFitness>3158490.0</TotalFitness>
    <BestFitness>29791.0</BestFitness>
  </Generation>
  <Generation>
    <AverageFitness>14069.3</AverageFitness>
    <TotalFitness>3517325.0</TotalFitness>
    <BestFitness>29791.0</BestFitness>
  </Generation>
  <Generation>
    <AverageFitness>14268.74</AverageFitness>
    <TotalFitness>3567185.0</TotalFitness>
    <BestFitness>21952.0</BestFitness>
  </Generation>
  <Generation>
    <AverageFitness>14395.624</AverageFitness>
    <TotalFitness>3598906.0</TotalFitness>
    <BestFitness>24389.0</BestFitness>
  </Generation>
  <Generation>
    <AverageFitness>15077.6</AverageFitness>
    <TotalFitness>3769400.0</TotalFitness>
    <BestFitness>35937.0</BestFitness>
  </Generation>
  <Generation>
    <AverageFitness>13875.048</AverageFitness>
    <TotalFitness>3468762.0</TotalFitness>
    <BestFitness>91125.0</BestFitness>
  </Generation>
  <Generation>
    <AverageFitness>13668.332</AverageFitness>
    <TotalFitness>3417083.0</TotalFitness>
    <BestFitness>27000.0</BestFitness>
  </Generation>
  <Generation>
    <AverageFitness>14689.736</AverageFitness>
    <TotalFitness>3672434.0</TotalFitness>
    <BestFitness>24389.0</BestFitness>
  </Generation>
  <Generation>
    <AverageFitness>13855.524</AverageFitness>
    <TotalFitness>3463881.0</TotalFitness>
    <BestFitness>27000.0</BestFitness>
  </Generation>
  <Generation>
    <AverageFitness>14300.272</AverageFitness>
    <TotalFitness>3575068.0</TotalFitness>
    <BestFitness>27000.0</BestFitness>
  </Generation>
  <Generation>
    <AverageFitness>14700.46</AverageFitness>
    <TotalFitness>3675115.0</TotalFitness>
    <BestFitness>27000.0</BestFitness>
  </Generation>
  <Generation>
    <AverageFitness>15200.12</AverageFitness>
    <TotalFitness>3800030.0</TotalFitness>
    <BestFitness>27000.0</BestFitness>
  </Generation>
  <Generation>
    <AverageFitness>15074.604</AverageFitness>
    <TotalFitness>3768651.0</TotalFitness>
    <BestFitness>32768.0</BestFitness>
  </Generation>
  <Generation>
    <AverageFitness>14818.908</AverageFitness>
    <TotalFitness>3704727.0</TotalFitness>
    <BestFitness>32768.0</BestFitness>
  </Generation>
  <Generation>
    <AverageFitness>14036.952</AverageFitness>
    <TotalFitness>3509238.0</TotalFitness>
    <BestFitness>24389.0</BestFitness>
  </Generation>
  <Generation>
    <AverageFitness>14205.332</AverageFitness>
    <TotalFitness>3551333.0</TotalFitness>
    <BestFitness>24389.0</BestFitness>
  </Generation>
</Training_Data>
